flipt/__init__.py
flipt/async_client.py
flipt/authentication/__init__.py
flipt/evaluation/__init__.py
flipt/evaluation/async_evaluation_client.py
flipt/evaluation/models.py
flipt/evaluation/sync_evaluation_client.py
flipt/exceptions.py
flipt/flags/__init__.py
flipt/flags/async_flag_client.py
flipt/flags/models.py
flipt/flags/sync_flag_client.py
flipt/models.py
flipt/py.typed
flipt/sync_client.py
flipt-1.6.0.dist-info/METADATA
flipt-1.6.0.dist-info/WHEEL
flipt-1.6.0.dist-info/entry_points.txt
flipt-1.6.0.dist-info/RECORD
