Metadata-Version: 2.1
Name: flipt
Version: 1.6.0
Summary: Flipt Server SDK
License: MIT
Author: Flipt Devs
Author-email: dev@flipt.io
Requires-Python: >=3.11,<4.0
Classifier: License :: OSI Approved :: MIT License
Classifier: Programming Language :: Python :: 3
Classifier: Programming Language :: Python :: 3.11
Classifier: Programming Language :: Python :: 3.12
Requires-Dist: httpx (>=0.27.0,<0.28.0)
Requires-Dist: pydantic (>=2.5.3,<3.0.0)
